cloudx_naas_api/__init__.py
cloudx_naas_api/geolocation.py
cloudx_naas_api/slice_management.py
cloudx_naas_api-1.2.9.data/scripts/cloudx
cloudx_naas_api-1.2.9.dist-info/LICENSE
cloudx_naas_api-1.2.9.dist-info/METADATA
cloudx_naas_api-1.2.9.dist-info/WHEEL
cloudx_naas_api-1.2.9.dist-info/top_level.txt
cloudx_naas_api-1.2.9.dist-info/RECORD
