Metadata-Version: 2.1
Name: cloudx-naas-api
Version: 1.2.9
Summary: CloudX Digital N+aaS API package
Home-page: https://github.com/cloudx/naas-api
Author: Umut Karabudak
Author-email: umut.karabudak@cloudx.com
License: UNKNOWN
Platform: UNKNOWN
Classifier: Programming Language :: Python :: 3
Classifier: License :: OSI Approved :: MIT License
Classifier: Operating System :: OS Independent
